{
  "totalCount": 29579,
  "generatedAt": "2026-03-14T05:12:42.466359+00:00",
  "sources": {
    "switchbrew": {
      "count": 2242,
      "fetchedAt": "2026-03-14T05:12:42.466359+00:00",
      "sourceUpdatedAt": "2025-06-05T05:14:00+00:00"
    },
    "nswdb": {
      "count": 3763,
      "fetchedAt": "2026-03-14T05:12:42.466359+00:00",
      "sourceUpdatedAt": null
    },
    "titledb": {
      "count": 27620,
      "fetchedAt": "2026-03-14T05:12:42.466359+00:00",
      "sourceUpdatedAt": "2026-03-13T07:24:42Z"
    }
  }
}